biomass/__init__.py
biomass/core.py
biomass/model_object.py
biomass/plotting.py
biomass/result.py
biomass/version.py
biomass/analysis/__init__.py
biomass/analysis/initial_condition.py
biomass/analysis/parameter.py
biomass/analysis/reaction.py
biomass/analysis/util.py
biomass/construction/__init__.py
biomass/construction/julia_template.py
biomass/construction/reaction_rules.py
biomass/construction/text2model.py
biomass/construction/thermodynamic_restrictions.py
biomass/construction/template/__init__.py
biomass/construction/template/observable.py
biomass/construction/template/ode.py
biomass/construction/template/problem.py
biomass/construction/template/reaction_network.py
biomass/construction/template/search_param.py
biomass/construction/template/viz.py
biomass/construction/template/name2idx/__init__.py
biomass/construction/template/name2idx/parameters.py
biomass/construction/template/name2idx/species.py
biomass/dynamics/__init__.py
biomass/dynamics/signaling_systems.py
biomass/dynamics/solver.py
biomass/dynamics/temporal_dynamics.py
biomass/estimation/__init__.py
biomass/estimation/optimizer.py
biomass/estimation/search_util.py
biomass/models/__init__.py
biomass/models/_copy.py
biomass/models/Nakakuki_Cell_2010/__init__.py
biomass/models/Nakakuki_Cell_2010/observable.py
biomass/models/Nakakuki_Cell_2010/ode.py
biomass/models/Nakakuki_Cell_2010/problem.py
biomass/models/Nakakuki_Cell_2010/reaction_network.py
biomass/models/Nakakuki_Cell_2010/search_param.py
biomass/models/Nakakuki_Cell_2010/viz.py
biomass/models/Nakakuki_Cell_2010/name2idx/__init__.py
biomass/models/Nakakuki_Cell_2010/name2idx/parameters.py
biomass/models/Nakakuki_Cell_2010/name2idx/species.py
biomass/models/circadian_clock/__init__.py
biomass/models/circadian_clock/observable.py
biomass/models/circadian_clock/ode.py
biomass/models/circadian_clock/problem.py
biomass/models/circadian_clock/reaction_network.py
biomass/models/circadian_clock/search_param.py
biomass/models/circadian_clock/viz.py
biomass-0.14.0.dist-info/LICENSE
biomass-0.14.0.dist-info/METADATA
biomass-0.14.0.dist-info/WHEEL
biomass-0.14.0.dist-info/top_level.txt
biomass-0.14.0.dist-info/RECORD
