Metadata-Version: 2.1
Name: biomass
Version: 0.14.0
Summary: A Python Framework for Modeling and Analysis of Signaling Systems
Author: Hiroaki Imoto
Maintainer-email: Hiroaki Imoto <hiroaki.imoto@ucd.ie>
License: Apache-2.0
Project-URL: repository, https://github.com/biomass-dev/biomass
Project-URL: documentation, https://biomass-core.readthedocs.io/en/latest/
Project-URL: bugtracker, https://github.com/biomass-dev/biomass/issues
Classifier: Development Status :: 4 - Beta
Classifier: Intended Audience :: Science/Research
Classifier: License :: OSI Approved :: Apache Software License
Classifier: Natural Language :: English
Classifier: Operating System :: OS Independent
Classifier: Programming Language :: Python :: 3
Classifier: Programming Language :: Python :: 3 :: Only
Classifier: Programming Language :: Python :: 3.8
Classifier: Programming Language :: Python :: 3.9
Classifier: Programming Language :: Python :: 3.10
Classifier: Programming Language :: Python :: 3.11
Classifier: Programming Language :: Python :: 3.12
Classifier: Topic :: Scientific/Engineering
Classifier: Topic :: Scientific/Engineering :: Bio-Informatics
Classifier: Topic :: Software Development
Classifier: Topic :: Software Development :: Libraries
Classifier: Topic :: Software Development :: Libraries :: Python Modules
Requires-Python: >=3.8
License-File: LICENSE
Requires-Dist: matplotlib>=3.0
Requires-Dist: numba>=0.56
Requires-Dist: numpy>=1.17
Requires-Dist: pandas>=0.24
Requires-Dist: scipy>=1.6
Requires-Dist: seaborn>=0.11.2
Requires-Dist: tqdm>=4.50.2
Requires-Dist: setuptools; python_version >= "3.12"
Provides-Extra: dev
Requires-Dist: black; extra == "dev"
Requires-Dist: flake8; extra == "dev"
Requires-Dist: isort; extra == "dev"
Requires-Dist: pre-commit; extra == "dev"
Requires-Dist: pytest; extra == "dev"
Provides-Extra: docs
Requires-Dist: sphinx; extra == "docs"
Requires-Dist: sphinx-rtd-theme>=1.2.0; extra == "docs"
Requires-Dist: sphinx-autodoc-typehints>=1.10.3; extra == "docs"
Requires-Dist: sphinxcontrib-bibtex>=2.2.0; extra == "docs"
Provides-Extra: graph
Requires-Dist: pygraphviz>=1.9; extra == "graph"
Requires-Dist: pyvis<0.3,>=0.2.1; extra == "graph"
